openconcept/__init__.py
openconcept/aerodynamics/CL_max_estimation.py
openconcept/aerodynamics/__init__.py
openconcept/aerodynamics/aerodynamics.py
openconcept/aerodynamics/drag_BWB.py
openconcept/aerodynamics/drag_jet_transport.py
openconcept/aerodynamics/openaerostruct/CL_max_critical_section.py
openconcept/aerodynamics/openaerostruct/__init__.py
openconcept/aerodynamics/openaerostruct/aerostructural.py
openconcept/aerodynamics/openaerostruct/drag_polar.py
openconcept/aerodynamics/openaerostruct/mesh_gen.py
openconcept/aerodynamics/openaerostruct/wave_drag.py
openconcept/atmospherics/__init__.py
openconcept/atmospherics/atmospherics_data.py
openconcept/atmospherics/compute_atmos_props.py
openconcept/atmospherics/density_comp.py
openconcept/atmospherics/dynamic_pressure_comp.py
openconcept/atmospherics/mach_number_comp.py
openconcept/atmospherics/pressure_comp.py
openconcept/atmospherics/speedofsound_comp.py
openconcept/atmospherics/temperature_comp.py
openconcept/atmospherics/true_airspeed.py
openconcept/costs/__init__.py
openconcept/costs/costs_commuter.py
openconcept/energy_storage/__init__.py
openconcept/energy_storage/battery.py
openconcept/energy_storage/hydrogen/LH2_tank_no_boil_off.py
openconcept/energy_storage/hydrogen/__init__.py
openconcept/energy_storage/hydrogen/structural.py
openconcept/energy_storage/hydrogen/tests/__init__.py
openconcept/energy_storage/hydrogen/tests/test_LH2_tank_no_boil_off.py
openconcept/energy_storage/hydrogen/tests/test_structural.py
openconcept/examples/B738.py
openconcept/examples/B738_VLM_drag.py
openconcept/examples/B738_aerostructural.py
openconcept/examples/B738_sizing.py
openconcept/examples/Caravan.py
openconcept/examples/ElectricSinglewithThermal.py
openconcept/examples/HybridTwin.py
openconcept/examples/HybridTwin_active_thermal.py
openconcept/examples/HybridTwin_thermal.py
openconcept/examples/KingAirC90GT.py
openconcept/examples/N3_HybridSingleAisle_Refrig.py
openconcept/examples/TBM850.py
openconcept-1.2.6.dist-info/licenses/LICENSE
openconcept-1.2.6.dist-info/METADATA
openconcept-1.2.6.dist-info/WHEEL
openconcept-1.2.6.dist-info/top_level.txt
openconcept-1.2.6.dist-info/RECORD
