Metadata-Version: 2.4
Name: openconcept
Version: 1.2.6
Summary: Open aircraft conceptual design tools
Home-page: https://github.com/mdolab/openconcept
Download-URL: https://github.com/mdolab/openconcept
Author: Benjamin J. Brelje and Eytan J. Adler
Author-email: 
License: MIT License
Keywords: aircraft design optimization multidisciplinary multi-disciplinary analysis
Classifier: Development Status :: 3 - Alpha
Classifier: Intended Audience :: Science/Research
Classifier: License :: OSI Approved :: MIT License
Classifier: Natural Language :: English
Classifier: Operating System :: MacOS :: MacOS X
Classifier: Operating System :: POSIX :: Linux
Classifier: Operating System :: Microsoft :: Windows
Classifier: Topic :: Scientific/Engineering
Classifier: Programming Language :: Python
Classifier: Programming Language :: Python :: 3.8
Classifier: Programming Language :: Python :: Implementation :: CPython
License-File: LICENSE
Requires-Dist: numpy<2,>=1.20
Requires-Dist: scipy>=1.7.0
Requires-Dist: openmdao>=3.21
Provides-Extra: testing
Requires-Dist: pytest; extra == "testing"
Requires-Dist: pytest-cov; extra == "testing"
Requires-Dist: coverage; extra == "testing"
Requires-Dist: openaerostruct; extra == "testing"
Requires-Dist: parameterized; extra == "testing"
Requires-Dist: om-pycycle>=4.4.0; extra == "testing"
Provides-Extra: docs
Requires-Dist: sphinx_mdolab_theme; extra == "docs"
Requires-Dist: openaerostruct<=2.7.1; extra == "docs"
Provides-Extra: plot
Requires-Dist: matplotlib; extra == "plot"
Dynamic: author
Dynamic: classifier
Dynamic: description
Dynamic: description-content-type
Dynamic: download-url
Dynamic: home-page
Dynamic: keywords
Dynamic: license
Dynamic: license-file
Dynamic: provides-extra
Dynamic: requires-dist
Dynamic: summary
